s3_ls/__init__.py
s3_ls/__main__.py
s3_ls-0.0.5.dist-info/licenses/LICENSE
s3_ls-0.0.5.dist-info/METADATA
s3_ls-0.0.5.dist-info/WHEEL
s3_ls-0.0.5.dist-info/entry_points.txt
s3_ls-0.0.5.dist-info/top_level.txt
s3_ls-0.0.5.dist-info/RECORD
