Metadata-Version: 2.4
Name: s3-ls
Version: 0.0.5
Summary: Fast S3 object listing
Author-email: Hanch Han <cndghks15@gmail.com>
License-Expression: MIT
Requires-Python: >=3.10
License-File: LICENSE
Requires-Dist: boto3
Requires-Dist: dotenv
Requires-Dist: tqdm
Dynamic: license-file
